srcinfo/__init__.py
srcinfo/main.py
srcinfo/parse.py
srcinfo/utils.py
srcinfo-0.1.2.dist-info/LICENSE
srcinfo-0.1.2.dist-info/METADATA
srcinfo-0.1.2.dist-info/WHEEL
srcinfo-0.1.2.dist-info/entry_points.txt
srcinfo-0.1.2.dist-info/RECORD
