Metadata-Version: 2.1
Name: srcinfo
Version: 0.1.2
Summary: A small library to parse .SRCINFO files
License: ISC
Author: Johannes Löthberg
Author-email: johannes@kyriasis.com
Requires-Python: >=3.7,<4.0
Classifier: Development Status :: 5 - Production/Stable
Classifier: License :: OSI Approved
Classifier: License :: OSI Approved :: ISC License (ISCL)
Classifier: Programming Language :: Python :: 3
Classifier: Programming Language :: Python :: 3.7
Classifier: Programming Language :: Python :: 3.8
Classifier: Programming Language :: Python :: 3.9
Classifier: Programming Language :: Python :: 3.10
Classifier: Programming Language :: Python :: 3.11
Classifier: Topic :: System :: Archiving :: Packaging
Requires-Dist: parse (>=1.19.0,<2.0.0)
